README.md
setup.py
logor/__init__.py
logor/version.py
logor.egg-info/PKG-INFO
logor.egg-info/SOURCES.txt
logor.egg-info/dependency_links.txt
logor.egg-info/entry_points.txt
logor.egg-info/top_level.txt
logor/core/__init__.py
logor/core/entry.py
logor/core/socket_manager.py
logor/hooks/__init__.py
logor/hooks/console.py
logor/hooks/file.py
logor/interface/__init__.py
logor/interface/hook.py
logor/utils/__init__.py
logor/utils/codec.py
logor/utils/common.py
test/test_1_for_basic.py