Metadata-Version: 1.1
Name: logor
Version: 0.0.5
Summary: This is a Log collector
Home-page: https://github.com/CzaOrz/Logor
Author: czaOrz
Author-email: 972542644@qq.com
License: UNKNOWN
Platform: UNKNOWN
Classifier: Programming Language :: Python :: 3.6
Classifier: Programming Language :: Python :: 3.7
